CHANGELOG.md
cdkata/__init__.py
cdkata/cli.py
cdkata-0.0.0.dist-info/entry_points.txt
cdkata-0.0.0.dist-info/LICENSE
cdkata-0.0.0.dist-info/WHEEL
cdkata-0.0.0.dist-info/METADATA
cdkata-0.0.0.dist-info/RECORD
